wfpm/__init__.py
wfpm/dependency.py
wfpm/git.py
wfpm/package.py
wfpm/project.py
wfpm/utils.py
wfpm/cli/__init__.py
wfpm/cli/init_cmd.py
wfpm/cli/install_cmd.py
wfpm/cli/list_cmd.py
wfpm/cli/new_cmd.py
wfpm/cli/nextver_cmd.py
wfpm/cli/outdated_cmd.py
wfpm/cli/test_cmd.py
wfpm/cli/uninstall_cmd.py
wfpm/cli/workon_cmd.py
wfpm/pkg_templates/__init__.py
wfpm/pkg_templates/project/cookiecutter.json
wfpm/pkg_templates/project/{{cookiecutter.project_slug}}/.gitignore
wfpm/pkg_templates/project/{{cookiecutter.project_slug}}/.wfpm
wfpm/pkg_templates/project/{{cookiecutter.project_slug}}/LICENSE
wfpm/pkg_templates/project/{{cookiecutter.project_slug}}/LICENSE-short
wfpm/pkg_templates/project/{{cookiecutter.project_slug}}/README.md
wfpm/pkg_templates/project/{{cookiecutter.project_slug}}/nextflow.config
wfpm/pkg_templates/project/{{cookiecutter.project_slug}}/.github/workflows/build-test-release.yml
wfpm/pkg_templates/project/{{cookiecutter.project_slug}}/scripts/cleanup_temp_files.sh
wfpm/pkg_templates/project/{{cookiecutter.project_slug}}/scripts/prepare_package_release_json.py
wfpm/pkg_templates/project/{{cookiecutter.project_slug}}/test_data/README.md
wfpm/pkg_templates/project/{{cookiecutter.project_slug}}/wfpr_modules/README.md
wfpm/pkg_templates/tool/cookiecutter.json
wfpm/pkg_templates/tool/{{cookiecutter._pkg_name}}/.dockerignore
wfpm/pkg_templates/tool/{{cookiecutter._pkg_name}}/Dockerfile
wfpm/pkg_templates/tool/{{cookiecutter._pkg_name}}/README.md
wfpm/pkg_templates/tool/{{cookiecutter._pkg_name}}/main.nf
wfpm/pkg_templates/tool/{{cookiecutter._pkg_name}}/main.py
wfpm/pkg_templates/tool/{{cookiecutter._pkg_name}}/nextflow.config
wfpm/pkg_templates/tool/{{cookiecutter._pkg_name}}/pkg.json
wfpm/pkg_templates/tool/{{cookiecutter._pkg_name}}/tests/checker.nf
wfpm/pkg_templates/tool/{{cookiecutter._pkg_name}}/tests/nextflow.config
wfpm/pkg_templates/tool/{{cookiecutter._pkg_name}}/tests/test-job-1.json
wfpm-0.8.0.dist-info/LICENSE.txt
wfpm-0.8.0.dist-info/METADATA
wfpm-0.8.0.dist-info/WHEEL
wfpm-0.8.0.dist-info/entry_points.txt
wfpm-0.8.0.dist-info/top_level.txt
wfpm-0.8.0.dist-info/zip-safe
wfpm-0.8.0.dist-info/RECORD
