Metadata-Version: 2.1
Name: wfpm
Version: 0.8.0
Summary: WorkFlow Package Manager
Home-page: https://github.com/icgc-argo/wfpm
License: Apache Software License 2.0
Platform: UNKNOWN
Classifier: Development Status :: 3 - Alpha
Classifier: Operating System :: OS Independent
Requires-Python: >=3.6
Requires-Dist: click (>=7.1.2)
Requires-Dist: PyYAML (>=5.3.1)
Requires-Dist: requests (>=2.25.1)
Requires-Dist: packaging (>=20.8)
Requires-Dist: cookiecutter (>=1.7.2)
Requires-Dist: networkx (>=2.5)
Requires-Dist: questionary (>=1.9.0)
